vc_hid/__init__.py
vc_hid/hid_tde.py
vc_hid/vc_hid.cp36-win32.pyd
vc_hid/vc_hid.dll
vc_hid-2022.2.1.dist-info/METADATA
vc_hid-2022.2.1.dist-info/WHEEL
vc_hid-2022.2.1.dist-info/top_level.txt
vc_hid-2022.2.1.dist-info/RECORD
