Metadata-Version: 2.1
Name: vc-hid
Version: 2022.2.1
Summary: USB HID command package
Home-page: https://github.com/Lorrytoolcenter/VC-HID.git
Author: lorry_rui
Author-email: lrui@logitech.com
License: UNKNOWN
Platform: UNKNOWN
Classifier: Programming Language :: Python :: 3.6
Classifier: License :: OSI Approved :: MIT License
Classifier: Operating System :: OS Independent
Requires-Python: >=3.5
